README.rst
setup.py
PSMNet2/__init__.py
PSMNet2/pretrained_model_KITTI2015.tar
PSMNet2/smd2.py
PSMNet2/models/__init__.py
PSMNet2/models/basic.py
PSMNet2/models/stackhourglass.py
PSMNet2/models/submodule.py
PSMNet2/utils/__init__.py
PSMNet2/utils/preprocess.py
PSMNet2/utils/readpfm.py
SMDTest.egg-info/PKG-INFO
SMDTest.egg-info/SOURCES.txt
SMDTest.egg-info/dependency_links.txt
SMDTest.egg-info/top_level.txt